AguaSpider/__init__.py
AguaSpider-0.0.1.dist-info/LICENSE
AguaSpider-0.0.1.dist-info/METADATA
AguaSpider-0.0.1.dist-info/WHEEL
AguaSpider-0.0.1.dist-info/top_level.txt
AguaSpider-0.0.1.dist-info/RECORD
