Metadata-Version: 2.1
Name: AguaSpider
Version: 0.0.1
Summary: A easy asynchronous spider 
Home-page: https://github.com/pypa/sampleproject
Author: FL_Agua
Author-email: Agua1101@sina.com
License: UNKNOWN
Platform: UNKNOWN
Classifier: Programming Language :: Python :: 3
Classifier: License :: OSI Approved :: MIT License
Classifier: Operating System :: OS Independent
